Emailio.py
Emailio-0.0.1.dist-info/License
Emailio-0.0.1.dist-info/METADATA
Emailio-0.0.1.dist-info/WHEEL
Emailio-0.0.1.dist-info/top_level.txt
Emailio-0.0.1.dist-info/RECORD
