Metadata-Version: 2.1
Name: Emailio
Version: 0.0.1
Summary: Emailio is a Python package that provides a simple and easy-to-use interface for sending emails with attachments. It uses the Simple Mail Transfer Protocol (SMTP) to send emails, and supports attachments of different file types.
Author: Ravi shanker Lal
Keywords: Send email,Sendemail,Send email with attachments,Mail
Classifier: Programming Language :: Python :: 3
Classifier: License :: OSI Approved :: MIT License
Classifier: Operating System :: OS Independent
Requires-Python: >=3.9
License-File: License
